[
  {
    "id": "6334b06b6e0b314b1e80e02c",
    "picture": "./push.jpg",
    "age": 29,
    "heading": "Dumble",
    "timeRequired": 30
  },
  {
    "id": "6334b06b0f471fccdd4cd130",
    "picture": "./push.jpg",
    "age": 22,
    "heading": "Dumble",
    "timeRequired": 30
  },
  {
    "id": "6334b06b94067719ab62d91a",
    "picture": "./push.jpg",
    "age": 30,
    "heading": "Dumble",
    "timeRequired": 30
  },
  {
    "id": "6334b06be9950cce8550c8ee",
    "picture": "./push.jpg",
    "age": 27,
    "heading": "Dumble",
    "timeRequired": 30
  },
  {
    "id": "6334b06b7e060bb0d22f4dec",
    "picture": "./push.jpg",
    "age": 26,
    "heading": "Dumble",
    "timeRequired": 30
  },
  {
    "id": "6334b06b08b843b536b8c41e",
    "picture": "./push.jpg",
    "age": 24,
    "heading": "Dumble",
    "timeRequired": 30
  }
]